<?xml version="1.0" encoding="utf-8"?>
<LanguageData>
  
  <Alien_Centaur.label>半人马</Alien_Centaur.label>
  <Alien_Centaur.description>一种极度罕见、不明来历的生物工程改造物种，拥有一个被追加了额外补丁的人类基因组，半人马被归类为一个独立的哺乳类物种。\n\n半人马拥有比人类更强大的体魄，普遍更优秀的外观，更能适应寒冷环境，更大的胃口和饭量，更强大的免疫力，比人类更难被击倒，完全免疫疼痛休克，同时也是天生的射击好手。尽管他们有着马的外观，但半人马是杂食性的。\n\n根据流言，半人马是一种超凡科技创造的人造物种，永生不朽且举世无敌，但同时也不具有生育能力。他们拥有极度强大的种族限定装备，使他们成为了宛若神明的存在——并且从来也没有人目击到或见过这些神。</Alien_Centaur.description>
  <Alien_Centaur.tools.0.label>左拳</Alien_Centaur.tools.0.label>
  <Alien_Centaur.tools.1.label>右拳</Alien_Centaur.tools.1.label>
  <Alien_Centaur.tools.2.label>牙齿</Alien_Centaur.tools.2.label>
  <Alien_Centaur.tools.3.label>头</Alien_Centaur.tools.3.label>
  <Alien_Centaur.tools.4.label>左前蹄</Alien_Centaur.tools.4.label>
  <Alien_Centaur.tools.5.label>右前蹄</Alien_Centaur.tools.5.label>
  <Alien_Centaur.tools.6.label>左后蹄</Alien_Centaur.tools.6.label>
  <Alien_Centaur.tools.7.label>右后蹄</Alien_Centaur.tools.7.label>
  
</LanguageData>